<?xml version="1.0" encoding="utf-8" ?>
<dwsync>
<file name="chart-area-demo.js" server="ftp.lucasrondon.com.br/lucasrondon.com.br/web/unibrasil/" local="131811057720000000" remote="131917135800000000" Dst="2" />
<file name="chart-bar-demo.js" server="ftp.lucasrondon.com.br/lucasrondon.com.br/web/unibrasil/" local="131811057720000000" remote="131917135800000000" Dst="2" />
<file name="datatables-demo.js" server="ftp.lucasrondon.com.br/lucasrondon.com.br/web/unibrasil/" local="131811057720000000" remote="131917135800000000" Dst="2" />
<file name="chart-pie-demo.js" server="ftp.lucasrondon.com.br/lucasrondon.com.br/web/unibrasil/" local="131811057720000000" remote="131917135800000000" Dst="2" />
<file name="chart-area-demo.js" server="ftp.cvsfotoyvideo.com/cvsfotoyvideo.com/web/" local="131811057720000000" remote="131920588200000000" Dst="2" />
<file name="chart-bar-demo.js" server="ftp.cvsfotoyvideo.com/cvsfotoyvideo.com/web/" local="131811057720000000" remote="131920588200000000" Dst="2" />
<file name="chart-pie-demo.js" server="ftp.cvsfotoyvideo.com/cvsfotoyvideo.com/web/" local="131811057720000000" remote="131920588200000000" Dst="2" />
<file name="datatables-demo.js" server="ftp.cvsfotoyvideo.com/cvsfotoyvideo.com/web/" local="131811057720000000" remote="131920588200000000" Dst="2" />
</dwsync>